setup.py
metamod/__init__.py
metamod/ops.py
metamod/row.py
metamod/stmt.py
metamod.egg-info/PKG-INFO
metamod.egg-info/SOURCES.txt
metamod.egg-info/dependency_links.txt
metamod.egg-info/entry_points.txt
metamod.egg-info/requires.txt
metamod.egg-info/top_level.txt
test/test_ops.py
test/test_row.py