Metadata-Version: 1.0
Name: metamod
Version: 0.0.2
Summary: ORM that uses __slots__ (for memory saving), plain DBAPI2 connections (to not break threading) and assumes the user knows SQL
Home-page: https://github.com/abe-winter/metamod
Author: Abe Winter
Author-email: awinter.public@gmail.com
License: MIT
Platform: UNKNOWN
